{
	"file_path": "C:\\Users\\Owner\\AppData\\Local\\Packages\\Microsoft.MinecraftUWP_8wekyb3d8bbwe\\LocalState\\games\\com.mojang\\development_behavior_packs\\More Enchantments Addon\\blocks\\warped_log.json",
	"file_type": "block",
	"format_version": 1,
	"file_uuid": "3a2b00a0_7f34_4315_80ae_ae29de081eb6",
	"file_version": 17,
	"cache_content": {
		"children": [
			{
				"data": "1.16.100",
				"key": "format_version"
			},
			{
				"open": {
					"format_version": "1.16.100",
					"minecraft:block": {
						"components": {
							"minecraft:block_light_absorption": 0,
							"minecraft:block_light_emission": 0,
							"minecraft:breakonpush": true,
							"minecraft:destroy_time": 1000,
							"minecraft:explosion_resistance": 0,
							"minecraft:flammable": {
								"burn_odds": 10,
								"flame_odds": 10
							},
							"minecraft:geometry": "geometry.log",
							"minecraft:material_instances": {
								"*": {
									"render_method": "alpha_test",
									"texture": "log"
								}
							},
							"minecraft:ticking": {
								"looping": true,
								"on_tick": {
									"event": "test",
									"target": "self"
								},
								"range": [
									0,
									0
								]
							},
							"minecraft:crafting_table": {
								"custom_description": "Arcane Table",
								"grid_size": 3,
								"crafting_tags": [
									"arcane_table"
								]
							}
						},
						"description": {
							"identifier": "ray:warped_log"
						},
						"events": {
							"test": {
								"run_command": {
									"command": [
										"setblock ~ ~ ~ structure_void",
										"structure load warped ~ ~ ~"
									]
								}
							}
						},
						"permutations": [
							{
								"components": {
									"minecraft:block_light_emission": 1
								}
							}
						]
					}
				},
				"key": "minecraft:block",
				"children": [
					{
						"open": {
							"components": {
								"minecraft:block_light_absorption": 0,
								"minecraft:block_light_emission": 0,
								"minecraft:breakonpush": true,
								"minecraft:destroy_time": 1000,
								"minecraft:explosion_resistance": 0,
								"minecraft:flammable": {
									"burn_odds": 10,
									"flame_odds": 10
								},
								"minecraft:geometry": "geometry.log",
								"minecraft:material_instances": {
									"*": {
										"render_method": "alpha_test",
										"texture": "log"
									}
								},
								"minecraft:ticking": {
									"looping": true,
									"on_tick": {
										"event": "test",
										"target": "self"
									},
									"range": [
										0,
										0
									]
								},
								"minecraft:crafting_table": {
									"custom_description": "Arcane Table",
									"grid_size": 3,
									"crafting_tags": [
										"arcane_table"
									]
								}
							},
							"description": {
								"identifier": "ray:warped_log"
							},
							"events": {
								"test": {
									"run_command": {
										"command": [
											"setblock ~ ~ ~ structure_void",
											"structure load warped ~ ~ ~"
										]
									}
								}
							},
							"permutations": [
								{
									"components": {
										"minecraft:block_light_emission": 1
									}
								}
							]
						},
						"key": "components",
						"is_minified": true,
						"children": {
							"minecraft:block_light_absorption": 0,
							"minecraft:block_light_emission": 0,
							"minecraft:breakonpush": true,
							"minecraft:destroy_time": 1000,
							"minecraft:explosion_resistance": 0,
							"minecraft:flammable": {
								"burn_odds": 10,
								"flame_odds": 10
							},
							"minecraft:geometry": "geometry.log",
							"minecraft:material_instances": {
								"*": {
									"render_method": "alpha_test",
									"texture": "log"
								}
							},
							"minecraft:ticking": {
								"looping": true,
								"on_tick": {
									"event": "test",
									"target": "self"
								},
								"range": [
									0,
									0
								]
							},
							"minecraft:crafting_table": {
								"custom_description": "Arcane Table",
								"grid_size": 3,
								"crafting_tags": [
									"arcane_table"
								]
							}
						}
					},
					{
						"open": {
							"components": {
								"minecraft:block_light_absorption": 0,
								"minecraft:block_light_emission": 0,
								"minecraft:breakonpush": true,
								"minecraft:destroy_time": 1000,
								"minecraft:explosion_resistance": 0,
								"minecraft:flammable": {
									"burn_odds": 10,
									"flame_odds": 10
								},
								"minecraft:geometry": "geometry.log",
								"minecraft:material_instances": {
									"*": {
										"render_method": "alpha_test",
										"texture": "log"
									}
								},
								"minecraft:ticking": {
									"looping": true,
									"on_tick": {
										"event": "test",
										"target": "self"
									},
									"range": [
										0,
										0
									]
								},
								"minecraft:crafting_table": {
									"custom_description": "Arcane Table",
									"grid_size": 3,
									"crafting_tags": [
										"arcane_table"
									]
								}
							},
							"description": {
								"identifier": "ray:warped_log"
							},
							"events": {
								"test": {
									"run_command": {
										"command": [
											"setblock ~ ~ ~ structure_void",
											"structure load warped ~ ~ ~"
										]
									}
								}
							},
							"permutations": [
								{
									"components": {
										"minecraft:block_light_emission": 1
									}
								}
							]
						},
						"key": "description",
						"is_minified": true,
						"children": {
							"identifier": "ray:warped_log"
						}
					},
					{
						"open": {
							"components": {
								"minecraft:block_light_absorption": 0,
								"minecraft:block_light_emission": 0,
								"minecraft:breakonpush": true,
								"minecraft:destroy_time": 1000,
								"minecraft:explosion_resistance": 0,
								"minecraft:flammable": {
									"burn_odds": 10,
									"flame_odds": 10
								},
								"minecraft:geometry": "geometry.log",
								"minecraft:material_instances": {
									"*": {
										"render_method": "alpha_test",
										"texture": "log"
									}
								},
								"minecraft:ticking": {
									"looping": true,
									"on_tick": {
										"event": "test",
										"target": "self"
									},
									"range": [
										0,
										0
									]
								},
								"minecraft:crafting_table": {
									"custom_description": "Arcane Table",
									"grid_size": 3,
									"crafting_tags": [
										"arcane_table"
									]
								}
							},
							"description": {
								"identifier": "ray:warped_log"
							},
							"events": {
								"test": {
									"run_command": {
										"command": [
											"setblock ~ ~ ~ structure_void",
											"structure load warped ~ ~ ~"
										]
									}
								}
							},
							"permutations": [
								{
									"components": {
										"minecraft:block_light_emission": 1
									}
								}
							]
						},
						"key": "events",
						"children": [
							{
								"open": {
									"test": {
										"run_command": {
											"command": [
												"setblock ~ ~ ~ structure_void",
												"structure load warped ~ ~ ~"
											]
										}
									}
								},
								"key": "test",
								"children": [
									{
										"open": {
											"run_command": {
												"command": [
													"setblock ~ ~ ~ structure_void",
													"structure load warped ~ ~ ~"
												]
											}
										},
										"key": "run_command",
										"children": [
											{
												"open": {
													"command": [
														"setblock ~ ~ ~ structure_void",
														"structure load warped ~ ~ ~"
													]
												},
												"key": "command",
												"is_minified": true,
												"children": [
													"setblock ~ ~ ~ structure_void",
													"structure load warped ~ ~ ~"
												]
											}
										]
									}
								]
							}
						]
					},
					{
						"key": "permutations",
						"is_minified": true,
						"children": [
							{
								"components": {
									"minecraft:block_light_emission": 1
								}
							}
						]
					}
				]
			}
		]
	}
}